wagen/__init__.py
wagen/almanac.py
wagen/caltopo_io.py
wagen/data.py
wagen/sun.py
wagen/timeline.py
wagen-0.1.0a5.dist-info/licenses/LICENSE
wagen-0.1.0a5.dist-info/WHEEL
wagen-0.1.0a5.dist-info/METADATA
wagen-0.1.0a5.dist-info/RECORD
