Metadata-Version: 2.4
Name: wagen
Version: 0.1.0a5
Summary: WAGEN (Wilderness Adventure GENerator)
Author: S.Pothier
Classifier: License :: OSI Approved :: MIT License
License-File: LICENSE
Requires-Dist: requests==2.32.3
